odoo/addons/supplier_calendar/README.rst
odoo/addons/supplier_calendar/__init__.py
odoo/addons/supplier_calendar/__manifest__.py
odoo/addons/supplier_calendar/i18n/supplier_calendar.pot
odoo/addons/supplier_calendar/models/__init__.py
odoo/addons/supplier_calendar/models/product.py
odoo/addons/supplier_calendar/models/purchase.py
odoo/addons/supplier_calendar/models/res_partner.py
odoo/addons/supplier_calendar/models/stock_rule.py
odoo/addons/supplier_calendar/readme/CONFIGURE.rst
odoo/addons/supplier_calendar/readme/CONTRIBUTORS.rst
odoo/addons/supplier_calendar/readme/DESCRIPTION.rst
odoo/addons/supplier_calendar/readme/USAGE.rst
odoo/addons/supplier_calendar/static/description/icon.png
odoo/addons/supplier_calendar/static/description/index.html
odoo/addons/supplier_calendar/tests/__init__.py
odoo/addons/supplier_calendar/tests/test_supplier_calendar.py
odoo/addons/supplier_calendar/views/product_view.xml
odoo/addons/supplier_calendar/views/res_partner_view.xml
odoo13_addon_supplier_calendar-13.0.1.0.1.dev6.dist-info/METADATA
odoo13_addon_supplier_calendar-13.0.1.0.1.dev6.dist-info/WHEEL
odoo13_addon_supplier_calendar-13.0.1.0.1.dev6.dist-info/top_level.txt
odoo13_addon_supplier_calendar-13.0.1.0.1.dev6.dist-info/RECORD
